{ "topSites": "{\"1951\":[{\"u\":\"classic.prisjakt.nu\",\"f\":111},{\"u\":\"www.bing.com\",\"f\":24},{\"u\":\"www.dwservice.net\",\"f\":21},{\"u\":\"node443189.dwservice.net\",\"f\":19},{\"u\":\"portalen.gotland.se\",\"f\":9},{\"u\":\"www.one-tab.com\",\"f\":5},{\"u\":\"docs.google.com\",\"f\":5},{\"u\":\"gist.github.com\",\"f\":4},{\"u\":\"www.youtube.com\",\"f\":4},{\"u\":\"textmechanic.com\",\"f\":4},{\"u\":\"en.luxuretv.com\",\"f\":3},{\"u\":\"www.netflix.com\",\"f\":3},{\"u\":\"x704.net\",\"f\":3},{\"u\":\"stackoverflow.com\",\"f\":2},{\"u\":\"www.geeksforgeeks.org\",\"f\":2},{\"u\":\"login.microsoftonline.com\",\"f\":2},{\"u\":\"outlook.office365.com\",\"f\":2},{\"u\":\"discussions.apple.com\",\"f\":2},{\"u\":\"www.instructables.com\",\"f\":2},{\"u\":\"jsonviewer.stack.hu\",\"f\":2},{\"u\":\"thispointer.com\",\"f\":1},{\"u\":\"node562925.dwservice.net\",\"f\":1},{\"u\":\"forum.plantuml.net\",\"f\":1},{\"u\":\"www.planttext.com\",\"f\":1},{\"u\":\"apple.stackexchange.com\",\"f\":1},{\"u\":\"graphcommons.com\",\"f\":1},{\"u\":\"store.google.com\",\"f\":1},{\"u\":\"www.androidauthority.com\",\"f\":1},{\"u\":\"ib.adnxs.com\",\"f\":1},{\"u\":\"www.chatmapper.com\",\"f\":1}],\"1952\":[{\"u\":\"myanimelist.net\",\"f\":82},{\"u\":\"www.newgrounds.com\",\"f\":36},{\"u\":\"www.dwservice.net\",\"f\":26},{\"u\":\"node443189.dwservice.net\",\"f\":23},{\"u\":\"darkanime.stream\",\"f\":14},{\"u\":\"madsans.com\",\"f\":14},{\"u\":\"www.patreon.com\",\"f\":12},{\"u\":\"best2019-games-web4.com\",\"f\":9},{\"u\":\"www.youtube.com\",\"f\":8},{\"u\":\"eh8jq4cmq8j9g5.com\",\"f\":8},{\"u\":\"flirtgirlsexxx2.com\",\"f\":5},{\"u\":\"adexchangegate.com\",\"f\":5},{\"u\":\"femefun.com\",\"f\":5},{\"u\":\"accounts.google.com\",\"f\":4},{\"u\":\"www.iwtserve.com\",\"f\":4},{\"u\":\"best.aliexpress.com\",\"f\":4},{\"u\":\"thebestgame2020.com\",\"f\":4},{\"u\":\"www.bing.com\",\"f\":4},{\"u\":\"www.pandorium.online\",\"f\":3},{\"u\":\"en.wikipedia.org\",\"f\":3},{\"u\":\"web.archive.org\",\"f\":3},{\"u\":\"www.crunchyroll.com\",\"f\":3},{\"u\":\"www.anime-planet.com\",\"f\":3},{\"u\":\"serve.popads.net\",\"f\":3},{\"u\":\"01mspmd5yalky8.com\",\"f\":3},{\"u\":\"ampugi334f.com\",\"f\":3},{\"u\":\"pervertslut.com\",\"f\":3},{\"u\":\"messages.google.com\",\"f\":3},{\"u\":\"www.hornygamer.com\",\"f\":2},{\"u\":\"www.igdb.com\",\"f\":2}],\"2001\":[{\"u\":\"www.bing.com\",\"f\":681},{\"u\":\"www.one-tab.com\",\"f\":36},{\"u\":\"xhamster.com\",\"f\":24},{\"u\":\"www.xvideos.com\",\"f\":20},{\"u\":\"node443189.dwservice.net\",\"f\":14},{\"u\":\"www.dwservice.net\",\"f\":12},{\"u\":\"www.tnaflix.com\",\"f\":10},{\"u\":\"www.youtube.com\",\"f\":10},{\"u\":\"classic.prisjakt.nu\",\"f\":10},{\"u\":\"www.pornhub.com\",\"f\":7},{\"u\":\"www.xnxx.com\",\"f\":4},{\"u\":\"www.empflix.com\",\"f\":4},{\"u\":\"www.spotify.com\",\"f\":3},{\"u\":\"www.tube8.com\",\"f\":2},{\"u\":\"www.youporn.com\",\"f\":2},{\"u\":\"s.opoxv.com\",\"f\":2},{\"u\":\"crptgate.com\",\"f\":2},{\"u\":\"cradver.livejasmin.com\",\"f\":2},{\"u\":\"www.newgrounds.com\",\"f\":2},{\"u\":\"iphonesexgames.com\",\"f\":2},{\"u\":\"www.last.fm\",\"f\":1},{\"u\":\"www.reddit.com\",\"f\":1},{\"u\":\"uploads.ungrounded.net\",\"f\":1},{\"u\":\"maps.org\",\"f\":1},{\"u\":\"www.healthline.com\",\"f\":1},{\"u\":\"support.google.com\",\"f\":1},{\"u\":\"www.messenger.com\",\"f\":1},{\"u\":\"electronics.stackexchange.com\",\"f\":1},{\"u\":\"www.alphaporno.com\",\"f\":1},{\"u\":\"www.ict-peces.eu\",\"f\":1}],\"2002\":[{\"u\":\"www.bing.com\",\"f\":1320},{\"u\":\"classic.prisjakt.nu\",\"f\":108},{\"u\":\"www.one-tab.com\",\"f\":103},{\"u\":\"www.dwservice.net\",\"f\":35},{\"u\":\"node443189.dwservice.net\",\"f\":33},{\"u\":\"www.tnaflix.com\",\"f\":16},{\"u\":\"www.youtube.com\",\"f\":14},{\"u\":\"www.last.fm\",\"f\":12},{\"u\":\"docs.google.com\",\"f\":11},{\"u\":\"todo.microsoft.com\",\"f\":10},{\"u\":\"to-do.microsoft.com\",\"f\":8},{\"u\":\"xhamster.com\",\"f\":6},{\"u\":\"cdon.se\",\"f\":4},{\"u\":\"serve.popads.net\",\"f\":4},{\"u\":\"darkanime.stream\",\"f\":4},{\"u\":\"madsans.com\",\"f\":4},{\"u\":\"www.iwtserve.com\",\"f\":4},{\"u\":\"eu.dspmulti.com\",\"f\":4},{\"u\":\"www.xvideos.com\",\"f\":3},{\"u\":\"clk.tradedoubler.com\",\"f\":3},{\"u\":\"www.how-fixit.com\",\"f\":3},{\"u\":\"www.spotify.com\",\"f\":3},{\"u\":\"www.empflix.com\",\"f\":2},{\"u\":\"www.komplett.se\",\"f\":2},{\"u\":\"www.proshop.se\",\"f\":2},{\"u\":\"www.facebook.com\",\"f\":2},{\"u\":\"5kv261gjmq04c9.com\",\"f\":2},{\"u\":\"aftonbladet.se.nyheter.sub.za.com\",\"f\":2},{\"u\":\"www.bet365.com\",\"f\":2},{\"u\":\"www.cam4.com\",\"f\":2}],\"2003\":[{\"u\":\"www.bing.com\",\"f\":129},{\"u\":\"www.dwservice.net\",\"f\":26},{\"u\":\"node443189.dwservice.net\",\"f\":21},{\"u\":\"www.one-tab.com\",\"f\":13},{\"u\":\"login.live.com\",\"f\":4},{\"u\":\"xhamster.com\",\"f\":4},{\"u\":\"www.youtube.com\",\"f\":3},{\"u\":\"portalen.gotland.se\",\"f\":3},{\"u\":\"www.xvideos.com\",\"f\":2},{\"u\":\"www.xtube.com\",\"f\":2},{\"u\":\"serve.popads.net\",\"f\":2},{\"u\":\"www.iwtserve.com\",\"f\":2},{\"u\":\"5kv261gjmq04c9.com\",\"f\":2},{\"u\":\"outlook.live.com\",\"f\":2},{\"u\":\"s.opoxv.com\",\"f\":1},{\"u\":\"crptgate.com\",\"f\":1},{\"u\":\"cradver.livejasmin.com\",\"f\":1},{\"u\":\"www.tnaflix.com\",\"f\":1},{\"u\":\"www.empflix.com\",\"f\":1},{\"u\":\"pr0pgutf0hp089.com\",\"f\":1},{\"u\":\"www.cam4.com\",\"f\":1},{\"u\":\"www.bet365.com\",\"f\":1},{\"u\":\"adexchangegate.com\",\"f\":1},{\"u\":\"ext.royalcactus.com\",\"f\":1},{\"u\":\"best2019-games-web4.com\",\"f\":1},{\"u\":\"trinikid.com\",\"f\":1},{\"u\":\"www.netflix.com\",\"f\":1},{\"u\":\"en.wikipedia.org\",\"f\":1},{\"u\":\"www.reddit.com\",\"f\":1},{\"u\":\"witcher.fandom.com\",\"f\":1}],\"2004\":[{\"u\":\"www.bing.com\",\"f\":178},{\"u\":\"www.xvideos.com\",\"f\":38},{\"u\":\"www.one-tab.com\",\"f\":15},{\"u\":\"animal-lovers.net\",\"f\":14},{\"u\":\"www.dwservice.net\",\"f\":8},{\"u\":\"fetish-world.org\",\"f\":7},{\"u\":\"node443189.dwservice.net\",\"f\":6},{\"u\":\"www.youporn.com\",\"f\":5},{\"u\":\"pervertslut.com\",\"f\":5},{\"u\":\"www.youtube.com\",\"f\":4},{\"u\":\"eroticasite.blogspot.com\",\"f\":3},{\"u\":\"zooextreme.net\",\"f\":3},{\"u\":\"s.opoxv.com\",\"f\":2},{\"u\":\"crptgate.com\",\"f\":2},{\"u\":\"cradver.livejasmin.com\",\"f\":2},{\"u\":\"drive.google.com\",\"f\":2},{\"u\":\"pornfay.org\",\"f\":2},{\"u\":\"zooskool.name\",\"f\":2},{\"u\":\"porncobra.com\",\"f\":2},{\"u\":\"www.pornhdvideos.net\",\"f\":2},{\"u\":\"aporntv.com\",\"f\":2},{\"u\":\"rpc-php.trafficfactory.biz\",\"f\":1},{\"u\":\"www.spotify.com\",\"f\":1},{\"u\":\"accounts.google.com\",\"f\":1},{\"u\":\"stackoverflow.com\",\"f\":1},{\"u\":\"mhtviewer.booogle.net\",\"f\":1},{\"u\":\"widget5.linkwithin.com\",\"f\":1},{\"u\":\"www.pornt.net\",\"f\":1},{\"u\":\"leporno.org\",\"f\":1},{\"u\":\"www.ampugi334f.com\",\"f\":1}],\"2005\":[{\"u\":\"www.dwservice.net\",\"f\":14},{\"u\":\"node443189.dwservice.net\",\"f\":11},{\"u\":\"www.one-tab.com\",\"f\":5},{\"u\":\"www.bing.com\",\"f\":1},{\"u\":\"xhamster.com\",\"f\":14},{\"u\":\"www.netflix.com\",\"f\":11},{\"u\":\"www.thermofisher.com\",\"f\":1},{\"u\":\"www.projectnoah.org\",\"f\":1},{\"u\":\"www.youtube.com\",\"f\":5},{\"u\":\"www.naturefootage.com\",\"f\":1},{\"u\":\"www.shutterstock.com\",\"f\":1},{\"u\":\"en.wikipedia.org\",\"f\":3},{\"u\":\"node710932.dwservice.net\",\"f\":5},{\"u\":\"textmechanic.com\",\"f\":2},{\"u\":\"www.ranknotebook.com\",\"f\":2},{\"u\":\"html-online.com\",\"f\":1},{\"u\":\"html5-editor.net\",\"f\":1},{\"u\":\"docs.google.com\",\"f\":4},{\"u\":\"www.spotify.com\",\"f\":1},{\"u\":\"www.ica.se\",\"f\":1},{\"u\":\"www.messenger.com\",\"f\":1},{\"u\":\"www.facebook.com\",\"f\":1}],\"2006\":[{\"u\":\"www.dwservice.net\",\"f\":25},{\"u\":\"www.bing.com\",\"f\":23},{\"u\":\"store.steampowered.com\",\"f\":15},{\"u\":\"node443189.dwservice.net\",\"f\":13},{\"u\":\"www.nexusmods.com\",\"f\":12},{\"u\":\"node562925.dwservice.net\",\"f\":10},{\"u\":\"www.youtube.com\",\"f\":9},{\"u\":\"www.netflix.com\",\"f\":6},{\"u\":\"www.g2a.com\",\"f\":5},{\"u\":\"users.nexusmods.com\",\"f\":5},{\"u\":\"www.pornhub.com\",\"f\":5},{\"u\":\"en.uesp.net\",\"f\":4},{\"u\":\"www.one-tab.com\",\"f\":4},{\"u\":\"neo4j.com\",\"f\":4},{\"u\":\"steamcommunity.com\",\"f\":3},{\"u\":\"www.hermods.se\",\"f\":3},{\"u\":\"www.dfworkshop.net\",\"f\":2},{\"u\":\"pervertslut.com\",\"f\":2},{\"u\":\"www.cpubenchmark.net\",\"f\":2},{\"u\":\"offerter.expertmarket.se\",\"f\":2},{\"u\":\"xxxbunker.com\",\"f\":2},{\"u\":\"web.unison.audio\",\"f\":1},{\"u\":\"workshop.upviral.com\",\"f\":1},{\"u\":\"www.pcgamer.com\",\"f\":1},{\"u\":\"www.rockpapershotgun.com\",\"f\":1},{\"u\":\"mail.google.com\",\"f\":1},{\"u\":\"steamdb.info\",\"f\":1},{\"u\":\"checkout.pay.g2a.com\",\"f\":1},{\"u\":\"supporthub.g2a.com\",\"f\":1},{\"u\":\"www.metro.se\",\"f\":1}],\"2007\":[{\"u\":\"www.bing.com\",\"f\":83},{\"u\":\"github.com\",\"f\":26},{\"u\":\"www.youtube.com\",\"f\":25},{\"u\":\"www.dwservice.net\",\"f\":23},{\"u\":\"node443189.dwservice.net\",\"f\":21},{\"u\":\"www.last.fm\",\"f\":11},{\"u\":\"www.one-tab.com\",\"f\":10},{\"u\":\"www.xvideos.com\",\"f\":10},{\"u\":\"www.pornhub.com\",\"f\":5},{\"u\":\"fatjoe.com\",\"f\":4},{\"u\":\"www.netflix.com\",\"f\":3},{\"u\":\"www.tampermonkey.net\",\"f\":3},{\"u\":\"en.uesp.net\",\"f\":2},{\"u\":\"www.facebook.com\",\"f\":2},{\"u\":\"www.messenger.com\",\"f\":2},{\"u\":\"greasyfork.org\",\"f\":2},{\"u\":\"www.spotify.com\",\"f\":2},{\"u\":\"www.paessler.com\",\"f\":2},{\"u\":\"try.wrike.com\",\"f\":2},{\"u\":\"superuser.com\",\"f\":2},{\"u\":\"node562925.dwservice.net\",\"f\":2},{\"u\":\"www.echoworx.com\",\"f\":1},{\"u\":\"circleci.com\",\"f\":1},{\"u\":\"accelbyte.io\",\"f\":1},{\"u\":\"www.ef.se\",\"f\":1},{\"u\":\"goose.game\",\"f\":1},{\"u\":\"www.g2a.com\",\"f\":1},{\"u\":\"www.reddit.com\",\"f\":1},{\"u\":\"www.intensivept.se\",\"f\":1},{\"u\":\"www.rulersofthesea.com\",\"f\":1}],\"2008\":[{\"u\":\"www.bing.com\",\"f\":143},{\"u\":\"www.skk.se\",\"f\":45},{\"u\":\"www.one-tab.com\",\"f\":26},{\"u\":\"www.dwservice.net\",\"f\":25},{\"u\":\"node443189.dwservice.net\",\"f\":22},{\"u\":\"www.youtube.com\",\"f\":18},{\"u\":\"www.blocket.se\",\"f\":11},{\"u\":\"stackoverflow.com\",\"f\":5},{\"u\":\"www.messenger.com\",\"f\":5},{\"u\":\"todo.microsoft.com\",\"f\":4},{\"u\":\"www.merrycocktails.se\",\"f\":4},{\"u\":\"www.antagning.se\",\"f\":4},{\"u\":\"www.w3resource.com\",\"f\":3},{\"u\":\"to-do.microsoft.com\",\"f\":3},{\"u\":\"zbporn.com\",\"f\":3},{\"u\":\"www.gunsans.se\",\"f\":3},{\"u\":\"www.sqlitetutorial.net\",\"f\":2},{\"u\":\"www.w3schools.com\",\"f\":2},{\"u\":\"github.com\",\"f\":2},{\"u\":\"developer.chrome.com\",\"f\":2},{\"u\":\"www.tnaflix.com\",\"f\":2},{\"u\":\"www.xtube.com\",\"f\":2},{\"u\":\"www.empflix.com\",\"f\":2},{\"u\":\"www.amazon.com\",\"f\":2},{\"u\":\"www.nudedxxx.com\",\"f\":2},{\"u\":\"vipergirls.to\",\"f\":2},{\"u\":\"www.manacas.se\",\"f\":2},{\"u\":\"www.tipzybandits.com\",\"f\":2},{\"u\":\"www.herdinginstincts.se\",\"f\":2},{\"u\":\"www.framtid.se\",\"f\":2}],\"2009\":[{\"u\":\"www.pornsos.com\",\"f\":102},{\"u\":\"www.dwservice.net\",\"f\":27},{\"u\":\"www.bing.com\",\"f\":24},{\"u\":\"www.kvalitetsdatorer.se\",\"f\":19},{\"u\":\"www.one-tab.com\",\"f\":17},{\"u\":\"classic.prisjakt.nu\",\"f\":16},{\"u\":\"www.youtube.com\",\"f\":13},{\"u\":\"www.elgiganten.se\",\"f\":12},{\"u\":\"stackoverflow.com\",\"f\":8},{\"u\":\"www.tube8.com\",\"f\":7},{\"u\":\"www.pornhub.com\",\"f\":7},{\"u\":\"cpu.userbenchmark.com\",\"f\":6},{\"u\":\"www.youporn.com\",\"f\":6},{\"u\":\"xhamster.com\",\"f\":5},{\"u\":\"www.proporn.com\",\"f\":5},{\"u\":\"www.gotporn.com\",\"f\":5},{\"u\":\"www.redtube.com\",\"f\":5},{\"u\":\"docs.microsoft.com\",\"f\":4},{\"u\":\"textmechanic.com\",\"f\":4},{\"u\":\"hotmovs.com\",\"f\":4},{\"u\":\"www.viptube.com\",\"f\":4},{\"u\":\"www.analdin.com\",\"f\":4},{\"u\":\"hclips.com\",\"f\":4},{\"u\":\"zbporn.com\",\"f\":3},{\"u\":\"jizzbunker.com\",\"f\":3},{\"u\":\"www.drtuber.com\",\"f\":3},{\"u\":\"anyporn.com\",\"f\":3},{\"u\":\"txxx.com\",\"f\":3},{\"u\":\"github.com\",\"f\":3},{\"u\":\"my.pornsos.com\",\"f\":3}],\"2010\":[{\"u\":\"www.dwservice.net\",\"f\":23},{\"u\":\"www.dietdoctor.com\",\"f\":10},{\"u\":\"www.youtube.com\",\"f\":9},{\"u\":\"www.postgresql.org\",\"f\":5},{\"u\":\"www.elgiganten.se\",\"f\":4},{\"u\":\"neo4j.com\",\"f\":3},{\"u\":\"docs.microsoft.com\",\"f\":2},{\"u\":\"wiki.postgresql.org\",\"f\":2},{\"u\":\"stackoverflow.com\",\"f\":2},{\"u\":\"alternativeto.net\",\"f\":2},{\"u\":\"www.coop.se\",\"f\":2},{\"u\":\"www.raymond.cc\",\"f\":2},{\"u\":\"www.spotify.com\",\"f\":1},{\"u\":\"www.renesas.com\",\"f\":1},{\"u\":\"pubs.acs.org\",\"f\":1},{\"u\":\"www.appannie.com\",\"f\":1},{\"u\":\"login.microsoftonline.com\",\"f\":1},{\"u\":\"www.mssqltips.com\",\"f\":1},{\"u\":\"www.cafe-encounter.net\",\"f\":1},{\"u\":\"pgxn.org\",\"f\":1},{\"u\":\"www.quora.com\",\"f\":1},{\"u\":\"holowczak.com\",\"f\":1},{\"u\":\"tdan.com\",\"f\":1},{\"u\":\"en.wikipedia.org\",\"f\":1},{\"u\":\"dbmstools.com\",\"f\":1},{\"u\":\"accelbyte.io\",\"f\":1},{\"u\":\"oribi.io\",\"f\":1},{\"u\":\"login.coop.se\",\"f\":1},{\"u\":\"www.dummies.com\",\"f\":1},{\"u\":\"markforged.com\",\"f\":1}],\"2011\":[{\"u\":\"www.dwservice.net\",\"f\":17},{\"u\":\"tempest.app\",\"f\":1},{\"u\":\"intra.gotland.se\",\"f\":2},{\"u\":\"idp.gotland.se\",\"f\":3},{\"u\":\"outlook.office.com\",\"f\":1},{\"u\":\"appsource.microsoft.com\",\"f\":4},{\"u\":\"login.microsoftonline.com\",\"f\":2},{\"u\":\"store.office.com\",\"f\":5},{\"u\":\"www.youtube.com\",\"f\":13},{\"u\":\"www.ajprodukter.se\",\"f\":1},{\"u\":\"www.hermods.se\",\"f\":1},{\"u\":\"www.pornsos.com\",\"f\":319},{\"u\":\"www.pornhub.com\",\"f\":2},{\"u\":\"xhamster.com\",\"f\":2},{\"u\":\"www.tube8.com\",\"f\":2},{\"u\":\"txxx.com\",\"f\":2},{\"u\":\"www.drtuber.com\",\"f\":2},{\"u\":\"jizzbunker.com\",\"f\":2},{\"u\":\"www.keezmovies.com\",\"f\":2},{\"u\":\"www.youporn.com\",\"f\":2},{\"u\":\"xxxdan.com\",\"f\":2},{\"u\":\"www.xtube.com\",\"f\":2},{\"u\":\"upornia.com\",\"f\":2},{\"u\":\"www.spankwire.com\",\"f\":2},{\"u\":\"www.redtube.com\",\"f\":2},{\"u\":\"www.gotporn.com\",\"f\":13},{\"u\":\"hotmovs.com\",\"f\":2},{\"u\":\"hclips.com\",\"f\":3},{\"u\":\"www.extremetube.com\",\"f\":2},{\"u\":\"www.one-tab.com\",\"f\":18},{\"u\":\"docs.microsoft.com\",\"f\":4},{\"u\":\"github.com\",\"f\":1},{\"u\":\"to-do.microsoft.com\",\"f\":6},{\"u\":\"my.pornsos.com\",\"f\":5},{\"u\":\"impactserving.com\",\"f\":1},{\"u\":\"crptgate.com\",\"f\":1},{\"u\":\"cradver.livejasmin.com\",\"f\":1},{\"u\":\"vrsimulatorer.se\",\"f\":1},{\"u\":\"www.paessler.com\",\"f\":1},{\"u\":\"www.viptube.com\",\"f\":1},{\"u\":\"www.bravoteens.com\",\"f\":1},{\"u\":\"hdzog.com\",\"f\":1},{\"u\":\"www.clipstudio.net\",\"f\":1},{\"u\":\"www.winporn.com\",\"f\":2},{\"u\":\"www.bravotube.net\",\"f\":2},{\"u\":\"www.nuvid.com\",\"f\":1},{\"u\":\"www.yeptube.com\",\"f\":2},{\"u\":\"anyporn.com\",\"f\":1},{\"u\":\"www.pornoxo.com\",\"f\":1},{\"u\":\"yourlust.com\",\"f\":1},{\"u\":\"www.analdin.com\",\"f\":1},{\"u\":\"www.vivatube.com\",\"f\":3},{\"u\":\"www.pornwatchers.com\",\"f\":1},{\"u\":\"www.pornrox.com\",\"f\":2},{\"u\":\"www.xozilla.com\",\"f\":1},{\"u\":\"www.pornhat.com\",\"f\":1},{\"u\":\"www.stileproject.com\",\"f\":1},{\"u\":\"www.hd21.com\",\"f\":1},{\"u\":\"www.iceporn.com\",\"f\":1},{\"u\":\"anysex.com\",\"f\":1},{\"u\":\"feeder.co\",\"f\":1},{\"u\":\"annihilvspowerelectronix.bandcamp.com\",\"f\":6},{\"u\":\"stackoverflow.com\",\"f\":11},{\"u\":\"dba.stackexchange.com\",\"f\":2},{\"u\":\"www.codeproject.com\",\"f\":1},{\"u\":\"www.sqlservertutorial.net\",\"f\":3},{\"u\":\"www.dietdoctor.com\",\"f\":2},{\"u\":\"dev.to\",\"f\":1},{\"u\":\"blog.jooq.org\",\"f\":1},{\"u\":\"www.gotlandshem.se\",\"f\":4},{\"u\":\"www.webmd.com\",\"f\":2},{\"u\":\"www.calvinklein.se\",\"f\":1},{\"u\":\"www.onenote.com\",\"f\":3},{\"u\":\"login.live.com\",\"f\":1},{\"u\":\"www.whathifi.com\",\"f\":1},{\"u\":\"opensource.com\",\"f\":1},{\"u\":\"www.muffsy.com\",\"f\":1},{\"u\":\"www.aliexpress.com\",\"f\":4},{\"u\":\"audioxpress.com\",\"f\":2},{\"u\":\"www.howtogeek.com\",\"f\":1},{\"u\":\"support.google.com\",\"f\":2},{\"u\":\"blog.floatingapps.net\",\"f\":1},{\"u\":\"www.quora.com\",\"f\":1},{\"u\":\"www.guidingtech.com\",\"f\":1},{\"u\":\"www.last.fm\",\"f\":14},{\"u\":\"odonisodonis.bandcamp.com\",\"f\":1},{\"u\":\"blackdresses.bandcamp.com\",\"f\":1},{\"u\":\"ironlungpv.bandcamp.com\",\"f\":1},{\"u\":\"infidelbodies.bandcamp.com\",\"f\":1},{\"u\":\"cracknationrecords.bandcamp.com\",\"f\":1}]}", "installDate": "1570325620847", "lastSeenVersion": "1.18", "settings": "{\"duplicates\":\"reject\"}", "extensionKey": "1d75e5fd-8a20-4c22-ba9c-85f897fbce6a", "state": {} }